pdf_parser_header_footer/__init__.py
pdf_parser_header_footer/config.py
pdf_parser_header_footer/parser.py
pdf_parser_header_footer/resources/es.zip
pdf_parser_header_footer/resources/line_joiner_model.pkl
pdf_parser_header_footer/resources/title_classifier_model.pkl
pdf_parser_header_footer/utils/__init__.py
pdf_parser_header_footer/utils/boundaries.py
pdf_parser_header_footer/utils/parse_to_markdown.py
pdf_parser_header_footer/utils/parse_to_markdown_utils.py
pdf_parser_header_footer/utils/pdf.py
pdf_parser_header_footer/utils/text.py
pdf_parser_header_footer/utils/visualization.py
pdf_parser_header_footer-0.2.0.dist-info/licenses/LICENSE
pdf_parser_header_footer-0.2.0.dist-info/METADATA
pdf_parser_header_footer-0.2.0.dist-info/WHEEL
pdf_parser_header_footer-0.2.0.dist-info/top_level.txt
pdf_parser_header_footer-0.2.0.dist-info/RECORD
