Metadata-Version: 2.4
Name: pdf_parser_header_footer
Version: 0.2.0
Summary: A Python package for processing PDFs with header and footer detection
Author: Tamara Orlich
Author-email: Tamara Orlich <tamara.orlich@borah.agency>
License: pdf-parser-header-footer
Project-URL: Homepage, https://github.com/BorahLabs/pdf_parser_with_header_footer/
Project-URL: Repository, https://github.com/BorahLabs/pdf_parser_with_header_footer/
Project-URL: Documentation, https://github.com/BorahLabs/pdf_parser_with_header_footer/#readme
Keywords: pdf,parser,text-extraction,document-processing
Requires-Python: >=3.8
License-File: LICENSE
Requires-Dist: pymupdf==1.25.4
Requires-Dist: pymupdf4llm==0.0.18
Requires-Dist: numpy>=2.0.0
Requires-Dist: pandas>=2.0.0
Requires-Dist: tqdm>=4.65.0
Requires-Dist: validators>=0.20.0
Requires-Dist: setuptools>=65.0.0
Requires-Dist: scikit-learn>=1.3.0
Dynamic: author
Dynamic: license-file
Dynamic: requires-python
